{
    "expanded": [
        "caminho-base",
        "laco_controle",
        "main_vet_iii"
    ],
    "tasks": {
        "tres": "10:0:0",
        "resto": "10:0:0",
        "media": "10:0:0",
        "sobrou": "10:0:0",
        "segundos": "10:0:0",
        "celsius": "10:0:0",
        "pintando": "10:0:0",
        "bala": "10:0:0",
        "abs": "1:0:0",
        "max": "10:0:100",
        "ou": "10:0:0",
        "positivo": "10:0:0",
        "multiplo": "10:0:0",
        "nulo": "10:0:0",
        "calculadora": "10:0:0",
        "guarda": "10:0:100",
        "quantos": "10:0:100",
        "impar": "10:0:100",
        "arredondar": "10:0:0",
        "mumia": "10:0:100",
        "meio": "10:0:100",
        "jokenpo": "10:0:100",
        "final": "10:0:0",
        "trabalhando": "10:0:0",
        "varetas": "10:0:0",
        "bhaskara": "10:0:100",
        "cortada": "9:0:100",
        "monica": "7:0:100",
        "drone": "9:0:100",
        "teleferico": "9:0:100",
        "goiabas": "9:0:100",
        "cobra": "9:0:100",
        "game10": "6:0:42",
        "salario": "10:0:100",
        "loop_i": "10:0:100",
        "pares": "10:0:100",
        "sapatos": "10:0:100",
        "filhos": "10:0:100",
        "ceu": "9:0:100",
        "esconde": "9:0:100",
        "zigzag": "10:0:100",
        "concentracao": "8:0:100",
        "lotado": "10:0:100",
        "sapinho": "9:0:100",
        "vet_i": "6:0:100",
        "vet_ii": "9:0:100",
        "vet_iii": "8:0:75",
        "apertada": "10:0:100",
        "dieta": "8:0:100",
        "patas": "7:0:100",
        "dindin": "8:0:100",
        "revolta": "10:0:100",
        "cartas": "8:0:100",
        "invertendo": "8:0:100",
        "fila": "6:0:60",
        "pedra": "2:0:0",
        "busca": "10:0:100",
        "contagem": "8:0:100",
        "xuxa": "10:0:100",
        "inverte": "10:0:100",
        "substring": "8:0:100",
        "ru": "8:0:100",
        "amora": "7:0:100",
        "quebrada": "10:0:0",
        "operacoes": "10:0:0",
        "data": "10:0:0",
        "opala": "10:0:0",
        "tv": "10:0:0",
        "impedido": "10:0:100",
        "maximo": "10:0:100",
        "chaves": "10:0:100",
        "chute": "10:0:100",
        "maior": "10:0:100",
        "morangos": "10:0:100",
        "zerinho": "10:0:100",
        "par": "10:0:100",
        "divisiveis": "10:0:100",
        "poco": "8:0:100",
        "primo": "9:0:100"
    },
    "flags": {
        "minimum": 0,
        "reward": 0,
        "percent": 0,
        "admin": 0,
        "config": 1,
        "skills": 0
    },
    "new_items": [
        "ponteiros",
        "vetor_busca",
        "main_sel_mod",
        "main_repii"
    ],
    "lang": "ts",
    "index": 18
}